setup.py
ssh_deploy/__init__.py
ssh_deploy/ssh.py
ssh_deploy/status.py
ssh_deploy.egg-info/PKG-INFO
ssh_deploy.egg-info/SOURCES.txt
ssh_deploy.egg-info/dependency_links.txt
ssh_deploy.egg-info/requires.txt
ssh_deploy.egg-info/top_level.txt