Metadata-Version: 1.0
Name: ssh-deploy
Version: 1.0.1
Summary: Automate tools for ssh deploy
Home-page: UNKNOWN
Author: blueszhangsh
Author-email: blues.zhang.sh@gmail.com
License: UNKNOWN
Platform: UNKNOWN
